{"dependencies":[{"name":"/Users/danminimac/code/alt-switch/.babelrc","includedInParent":true,"mtime":1520341508000},{"name":"/Users/danminimac/code/alt-switch/package.json","includedInParent":true,"mtime":1520341481000},{"name":"../learn-dom.js","loc":{"line":1,"column":20}},{"name":"../../store/store-repo.js","loc":{"line":2,"column":22}},{"name":"../../utils/utils.js","loc":{"line":3,"column":22}},{"name":"../learn-actions.js","loc":{"line":4,"column":24}},{"name":"../learn-types.js","loc":{"line":5,"column":22}}],"generated":{"js":"'use strict';\n\nObject.defineProperty(exports, \"__esModule\", {\n    value: true\n});\nexports.renderTextEntry = undefined;\n\nvar _learnDom = require('../learn-dom.js');\n\nvar _storeRepo = require('../../store/store-repo.js');\n\nvar _utils = require('../../utils/utils.js');\n\nvar _learnActions = require('../learn-actions.js');\n\nvar _learnTypes = require('../learn-types.js');\n\nvar renderTextEntry = exports.renderTextEntry = function renderTextEntry() {\n    var _store$getState = _storeRepo.store.getState(),\n        strategy = _store$getState.strategy,\n        item = _store$getState.item,\n        type = _store$getState.type;\n\n    if (type === _learnTypes.types.NEXT_ITEM) {\n\n        var sendQandA = null;\n\n        var handleEnterPress = function handleEnterPress(event) {\n            if (event.key === 'Enter') {\n                sendQandA();\n            }\n        };\n\n        var _store$getState2 = _storeRepo.store.getState(),\n            _strategy = _store$getState2.strategy;\n\n        var element = _strategy.elements.filter(function (el) {\n            return el.name === 'text-entry';\n        })[0];\n\n        if (!element) return;\n\n        var template = document.querySelector('.' + element.template);\n\n        sendQandA = function sendQandA() {\n            if (!document.querySelector('.js-txt-input')) return;\n\n            var _store$getState3 = _storeRepo.store.getState(),\n                item = _store$getState3.item;\n\n            var answer = document.querySelector('.js-txt-input').value;\n            var qandA = { question: item[element.question], answer: answer };\n            _learnActions.actions.boundMarkAnswer(qandA);\n        };\n\n        // window.addEventListener('keypress', handleEnterPress);\n\n        template.content.querySelector('span').innerHTML = item.genus;\n\n        var clone = document.importNode(template.content, true);\n\n        clone.querySelector('button').addEventListener('click', function (event) {\n            sendQandA();\n        });\n\n        element.parent.innerHTML = '';\n        element.parent.appendChild(clone);\n\n        document.querySelector('.js-txt-input').focus();\n    }\n};","map":{"mappings":[{"generated":{"line":8,"column":0},"source":"screens/text-entry.js","original":{"line":1,"column":0}},{"generated":{"line":10,"column":0},"source":"screens/text-entry.js","original":{"line":2,"column":0}},{"generated":{"line":12,"column":0},"source":"screens/text-entry.js","original":{"line":3,"column":0}},{"generated":{"line":14,"column":0},"source":"screens/text-entry.js","original":{"line":4,"column":0}},{"generated":{"line":16,"column":0},"source":"screens/text-entry.js","original":{"line":5,"column":0}},{"generated":{"line":18,"column":0},"source":"screens/text-entry.js","original":{"line":7,"column":7}},{"name":"renderTextEntry","generated":{"line":18,"column":4},"source":"screens/text-entry.js","original":{"line":7,"column":13}},{"generated":{"line":18,"column":48},"source":"screens/text-entry.js","original":{"line":7,"column":31}},{"name":"renderTextEntry","generated":{"line":18,"column":57},"source":"screens/text-entry.js","original":{"line":7,"column":13}},{"generated":{"line":18,"column":72},"source":"screens/text-entry.js","original":{"line":7,"column":31}},{"generated":{"line":18,"column":75},"source":"screens/text-entry.js","original":{"line":7,"column":37}},{"generated":{"line":19,"column":0},"source":"screens/text-entry.js","original":{"line":7,"column":37}},{"generated":{"line":19,"column":26},"source":"screens/text-entry.js","original":{"line":9,"column":37}},{"name":"getState","generated":{"line":19,"column":43},"source":"screens/text-entry.js","original":{"line":9,"column":43}},{"generated":{"line":19,"column":51},"source":"screens/text-entry.js","original":{"line":9,"column":37}},{"generated":{"line":19,"column":53},"source":"screens/text-entry.js","original":{"line":7,"column":37}},{"generated":{"line":20,"column":0},"source":"screens/text-entry.js","original":{"line":7,"column":37}},{"name":"strategy","generated":{"line":20,"column":8},"source":"screens/text-entry.js","original":{"line":9,"column":12}},{"generated":{"line":20,"column":16},"source":"screens/text-entry.js","original":{"line":7,"column":37}},{"name":"strategy","generated":{"line":20,"column":35},"source":"screens/text-entry.js","original":{"line":9,"column":12}},{"generated":{"line":20,"column":43},"source":"screens/text-entry.js","original":{"line":7,"column":37}},{"generated":{"line":21,"column":0},"source":"screens/text-entry.js","original":{"line":7,"column":37}},{"name":"item","generated":{"line":21,"column":8},"source":"screens/text-entry.js","original":{"line":9,"column":22}},{"generated":{"line":21,"column":12},"source":"screens/text-entry.js","original":{"line":7,"column":37}},{"name":"item","generated":{"line":21,"column":31},"source":"screens/text-entry.js","original":{"line":9,"column":22}},{"generated":{"line":21,"column":35},"source":"screens/text-entry.js","original":{"line":7,"column":37}},{"generated":{"line":22,"column":0},"source":"screens/text-entry.js","original":{"line":7,"column":37}},{"name":"type","generated":{"line":22,"column":8},"source":"screens/text-entry.js","original":{"line":9,"column":28}},{"generated":{"line":22,"column":12},"source":"screens/text-entry.js","original":{"line":7,"column":37}},{"name":"type","generated":{"line":22,"column":31},"source":"screens/text-entry.js","original":{"line":9,"column":28}},{"generated":{"line":22,"column":35},"source":"screens/text-entry.js","original":{"line":7,"column":37}},{"generated":{"line":24,"column":0},"source":"screens/text-entry.js","original":{"line":11,"column":4}},{"name":"type","generated":{"line":24,"column":8},"source":"screens/text-entry.js","original":{"line":11,"column":7}},{"generated":{"line":24,"column":17},"source":"screens/text-entry.js","original":{"line":11,"column":16}},{"name":"NEXT_ITEM","generated":{"line":24,"column":35},"source":"screens/text-entry.js","original":{"line":11,"column":22}},{"generated":{"line":24,"column":44},"source":"screens/text-entry.js","original":{"line":11,"column":4}},{"generated":{"line":24,"column":46},"source":"screens/text-entry.js","original":{"line":11,"column":33}},{"generated":{"line":26,"column":0},"source":"screens/text-entry.js","original":{"line":13,"column":8}},{"name":"sendQandA","generated":{"line":26,"column":12},"source":"screens/text-entry.js","original":{"line":13,"column":12}},{"generated":{"line":26,"column":24},"source":"screens/text-entry.js","original":{"line":13,"column":24}},{"generated":{"line":26,"column":28},"source":"screens/text-entry.js","original":{"line":13,"column":8}},{"generated":{"line":28,"column":0},"source":"screens/text-entry.js","original":{"line":15,"column":8}},{"name":"handleEnterPress","generated":{"line":28,"column":12},"source":"screens/text-entry.js","original":{"line":15,"column":14}},{"generated":{"line":28,"column":31},"source":"screens/text-entry.js","original":{"line":15,"column":33}},{"name":"handleEnterPress","generated":{"line":28,"column":40},"source":"screens/text-entry.js","original":{"line":15,"column":14}},{"generated":{"line":28,"column":56},"source":"screens/text-entry.js","original":{"line":15,"column":33}},{"generated":{"line":28,"column":64},"source":"screens/text-entry.js","original":{"line":15,"column":42}},{"generated":{"line":29,"column":0},"source":"screens/text-entry.js","original":{"line":16,"column":12}},{"name":"event","generated":{"line":29,"column":16},"source":"screens/text-entry.js","original":{"line":16,"column":15}},{"name":"key","generated":{"line":29,"column":22},"source":"screens/text-entry.js","original":{"line":16,"column":21}},{"generated":{"line":29,"column":25},"source":"screens/text-entry.js","original":{"line":16,"column":15}},{"generated":{"line":29,"column":30},"source":"screens/text-entry.js","original":{"line":16,"column":29}},{"generated":{"line":29,"column":37},"source":"screens/text-entry.js","original":{"line":16,"column":12}},{"generated":{"line":29,"column":39},"source":"screens/text-entry.js","original":{"line":16,"column":38}},{"name":"sendQandA","generated":{"line":30,"column":0},"source":"screens/text-entry.js","original":{"line":17,"column":16}},{"generated":{"line":31,"column":0},"source":"screens/text-entry.js","original":{"line":18,"column":13}},{"generated":{"line":32,"column":0},"source":"screens/text-entry.js","original":{"line":19,"column":9}},{"generated":{"line":32,"column":9},"source":"screens/text-entry.js","original":{"line":15,"column":8}},{"generated":{"line":34,"column":0},"source":"screens/text-entry.js","original":{"line":11,"column":33}},{"generated":{"line":34,"column":31},"source":"screens/text-entry.js","original":{"line":21,"column":29}},{"name":"getState","generated":{"line":34,"column":48},"source":"screens/text-entry.js","original":{"line":21,"column":35}},{"generated":{"line":34,"column":56},"source":"screens/text-entry.js","original":{"line":21,"column":29}},{"generated":{"line":34,"column":58},"source":"screens/text-entry.js","original":{"line":11,"column":33}},{"generated":{"line":35,"column":0},"source":"screens/text-entry.js","original":{"line":11,"column":33}},{"name":"strategy","generated":{"line":35,"column":12},"source":"screens/text-entry.js","original":{"line":21,"column":16}},{"generated":{"line":35,"column":21},"source":"screens/text-entry.js","original":{"line":11,"column":33}},{"name":"strategy","generated":{"line":35,"column":41},"source":"screens/text-entry.js","original":{"line":21,"column":16}},{"generated":{"line":35,"column":49},"source":"screens/text-entry.js","original":{"line":11,"column":33}},{"generated":{"line":37,"column":0},"source":"screens/text-entry.js","original":{"line":23,"column":8}},{"name":"element","generated":{"line":37,"column":12},"source":"screens/text-entry.js","original":{"line":23,"column":14}},{"name":"strategy","generated":{"line":37,"column":22},"source":"screens/text-entry.js","original":{"line":23,"column":24}},{"name":"elements","generated":{"line":37,"column":32},"source":"screens/text-entry.js","original":{"line":23,"column":33}},{"generated":{"line":37,"column":40},"source":"screens/text-entry.js","original":{"line":23,"column":24}},{"name":"filter","generated":{"line":37,"column":41},"source":"screens/text-entry.js","original":{"line":23,"column":42}},{"generated":{"line":37,"column":47},"source":"screens/text-entry.js","original":{"line":23,"column":24}},{"generated":{"line":37,"column":48},"source":"screens/text-entry.js","original":{"line":23,"column":49}},{"generated":{"line":38,"column":0},"source":"screens/text-entry.js","original":{"line":23,"column":49}},{"name":"el","generated":{"line":38,"column":19},"source":"screens/text-entry.js","original":{"line":23,"column":55}},{"name":"name","generated":{"line":38,"column":22},"source":"screens/text-entry.js","original":{"line":23,"column":58}},{"generated":{"line":38,"column":26},"source":"screens/text-entry.js","original":{"line":23,"column":55}},{"generated":{"line":38,"column":31},"source":"screens/text-entry.js","original":{"line":23,"column":67}},{"generated":{"line":38,"column":43},"source":"screens/text-entry.js","original":{"line":23,"column":49}},{"generated":{"line":39,"column":0},"source":"screens/text-entry.js","original":{"line":23,"column":49}},{"generated":{"line":39,"column":9},"source":"screens/text-entry.js","original":{"line":23,"column":24}},{"generated":{"line":39,"column":11},"source":"screens/text-entry.js","original":{"line":23,"column":81}},{"generated":{"line":39,"column":12},"source":"screens/text-entry.js","original":{"line":23,"column":24}},{"generated":{"line":39,"column":13},"source":"screens/text-entry.js","original":{"line":23,"column":8}},{"generated":{"line":41,"column":0},"source":"screens/text-entry.js","original":{"line":25,"column":8}},{"generated":{"line":41,"column":12},"source":"screens/text-entry.js","original":{"line":25,"column":11}},{"name":"element","generated":{"line":41,"column":13},"source":"screens/text-entry.js","original":{"line":25,"column":12}},{"generated":{"line":41,"column":20},"source":"screens/text-entry.js","original":{"line":25,"column":8}},{"generated":{"line":41,"column":22},"source":"screens/text-entry.js","original":{"line":25,"column":21}},{"generated":{"line":43,"column":0},"source":"screens/text-entry.js","original":{"line":27,"column":8}},{"name":"template","generated":{"line":43,"column":12},"source":"screens/text-entry.js","original":{"line":27,"column":14}},{"name":"document","generated":{"line":43,"column":23},"source":"screens/text-entry.js","original":{"line":27,"column":25}},{"name":"querySelector","generated":{"line":43,"column":32},"source":"screens/text-entry.js","original":{"line":27,"column":34}},{"generated":{"line":43,"column":45},"source":"screens/text-entry.js","original":{"line":27,"column":25}},{"name":"element","generated":{"line":43,"column":52},"source":"screens/text-entry.js","original":{"line":27,"column":52}},{"name":"template","generated":{"line":43,"column":60},"source":"screens/text-entry.js","original":{"line":27,"column":60}},{"generated":{"line":43,"column":68},"source":"screens/text-entry.js","original":{"line":27,"column":25}},{"generated":{"line":43,"column":69},"source":"screens/text-entry.js","original":{"line":27,"column":8}},{"name":"sendQandA","generated":{"line":45,"column":0},"source":"screens/text-entry.js","original":{"line":29,"column":8}},{"generated":{"line":45,"column":20},"source":"screens/text-entry.js","original":{"line":29,"column":20}},{"generated":{"line":45,"column":41},"source":"screens/text-entry.js","original":{"line":29,"column":26}},{"generated":{"line":46,"column":0},"source":"screens/text-entry.js","original":{"line":30,"column":12}},{"generated":{"line":46,"column":16},"source":"screens/text-entry.js","original":{"line":30,"column":15}},{"name":"document","generated":{"line":46,"column":17},"source":"screens/text-entry.js","original":{"line":30,"column":16}},{"name":"querySelector","generated":{"line":46,"column":26},"source":"screens/text-entry.js","original":{"line":30,"column":25}},{"generated":{"line":46,"column":39},"source":"screens/text-entry.js","original":{"line":30,"column":16}},{"generated":{"line":46,"column":40},"source":"screens/text-entry.js","original":{"line":30,"column":39}},{"generated":{"line":46,"column":55},"source":"screens/text-entry.js","original":{"line":30,"column":16}},{"generated":{"line":46,"column":56},"source":"screens/text-entry.js","original":{"line":30,"column":12}},{"generated":{"line":46,"column":58},"source":"screens/text-entry.js","original":{"line":30,"column":57}},{"generated":{"line":48,"column":0},"source":"screens/text-entry.js","original":{"line":29,"column":26}},{"generated":{"line":48,"column":35},"source":"screens/text-entry.js","original":{"line":31,"column":29}},{"name":"getState","generated":{"line":48,"column":52},"source":"screens/text-entry.js","original":{"line":31,"column":35}},{"generated":{"line":48,"column":60},"source":"screens/text-entry.js","original":{"line":31,"column":29}},{"generated":{"line":48,"column":62},"source":"screens/text-entry.js","original":{"line":29,"column":26}},{"generated":{"line":49,"column":0},"source":"screens/text-entry.js","original":{"line":29,"column":26}},{"name":"item","generated":{"line":49,"column":16},"source":"screens/text-entry.js","original":{"line":31,"column":20}},{"generated":{"line":49,"column":20},"source":"screens/text-entry.js","original":{"line":29,"column":26}},{"name":"item","generated":{"line":49,"column":40},"source":"screens/text-entry.js","original":{"line":31,"column":20}},{"generated":{"line":49,"column":44},"source":"screens/text-entry.js","original":{"line":29,"column":26}},{"generated":{"line":51,"column":0},"source":"screens/text-entry.js","original":{"line":32,"column":12}},{"name":"answer","generated":{"line":51,"column":16},"source":"screens/text-entry.js","original":{"line":32,"column":18}},{"name":"document","generated":{"line":51,"column":25},"source":"screens/text-entry.js","original":{"line":32,"column":27}},{"name":"querySelector","generated":{"line":51,"column":34},"source":"screens/text-entry.js","original":{"line":32,"column":36}},{"generated":{"line":51,"column":47},"source":"screens/text-entry.js","original":{"line":32,"column":27}},{"generated":{"line":51,"column":48},"source":"screens/text-entry.js","original":{"line":32,"column":50}},{"generated":{"line":51,"column":63},"source":"screens/text-entry.js","original":{"line":32,"column":27}},{"name":"value","generated":{"line":51,"column":65},"source":"screens/text-entry.js","original":{"line":32,"column":67}},{"generated":{"line":51,"column":70},"source":"screens/text-entry.js","original":{"line":32,"column":12}},{"generated":{"line":52,"column":0},"source":"screens/text-entry.js","original":{"line":33,"column":12}},{"name":"qandA","generated":{"line":52,"column":16},"source":"screens/text-entry.js","original":{"line":33,"column":18}},{"generated":{"line":52,"column":24},"source":"screens/text-entry.js","original":{"line":33,"column":26}},{"name":"question","generated":{"line":52,"column":26},"source":"screens/text-entry.js","original":{"line":33,"column":28}},{"name":"item","generated":{"line":52,"column":36},"source":"screens/text-entry.js","original":{"line":33,"column":38}},{"name":"element","generated":{"line":52,"column":41},"source":"screens/text-entry.js","original":{"line":33,"column":43}},{"name":"question","generated":{"line":52,"column":49},"source":"screens/text-entry.js","original":{"line":33,"column":51}},{"generated":{"line":52,"column":57},"source":"screens/text-entry.js","original":{"line":33,"column":38}},{"generated":{"line":52,"column":58},"source":"screens/text-entry.js","original":{"line":33,"column":26}},{"name":"answer","generated":{"line":52,"column":60},"source":"screens/text-entry.js","original":{"line":33,"column":62}},{"name":"answer","generated":{"line":52,"column":68},"source":"screens/text-entry.js","original":{"line":33,"column":70}},{"generated":{"line":52,"column":74},"source":"screens/text-entry.js","original":{"line":33,"column":26}},{"generated":{"line":52,"column":76},"source":"screens/text-entry.js","original":{"line":33,"column":12}},{"generated":{"line":53,"column":0},"source":"screens/text-entry.js","original":{"line":34,"column":12}},{"name":"boundMarkAnswer","generated":{"line":53,"column":34},"source":"screens/text-entry.js","original":{"line":34,"column":20}},{"generated":{"line":53,"column":49},"source":"screens/text-entry.js","original":{"line":34,"column":12}},{"name":"qandA","generated":{"line":53,"column":50},"source":"screens/text-entry.js","original":{"line":34,"column":36}},{"generated":{"line":53,"column":55},"source":"screens/text-entry.js","original":{"line":34,"column":12}},{"generated":{"line":54,"column":0},"source":"screens/text-entry.js","original":{"line":35,"column":9}},{"generated":{"line":54,"column":9},"source":"screens/text-entry.js","original":{"line":29,"column":8}},{"generated":{"line":56,"column":0},"source":"screens/text-entry.js","original":{"line":37,"column":8}},{"name":"template","generated":{"line":58,"column":0},"source":"screens/text-entry.js","original":{"line":39,"column":8}},{"name":"content","generated":{"line":58,"column":17},"source":"screens/text-entry.js","original":{"line":39,"column":17}},{"generated":{"line":58,"column":24},"source":"screens/text-entry.js","original":{"line":39,"column":8}},{"name":"querySelector","generated":{"line":58,"column":25},"source":"screens/text-entry.js","original":{"line":39,"column":25}},{"generated":{"line":58,"column":38},"source":"screens/text-entry.js","original":{"line":39,"column":8}},{"generated":{"line":58,"column":39},"source":"screens/text-entry.js","original":{"line":39,"column":39}},{"generated":{"line":58,"column":45},"source":"screens/text-entry.js","original":{"line":39,"column":8}},{"name":"innerHTML","generated":{"line":58,"column":47},"source":"screens/text-entry.js","original":{"line":39,"column":47}},{"generated":{"line":58,"column":56},"source":"screens/text-entry.js","original":{"line":39,"column":8}},{"name":"item","generated":{"line":58,"column":59},"source":"screens/text-entry.js","original":{"line":39,"column":59}},{"name":"genus","generated":{"line":58,"column":64},"source":"screens/text-entry.js","original":{"line":39,"column":64}},{"generated":{"line":58,"column":69},"source":"screens/text-entry.js","original":{"line":39,"column":8}},{"generated":{"line":60,"column":0},"source":"screens/text-entry.js","original":{"line":41,"column":8}},{"name":"clone","generated":{"line":60,"column":12},"source":"screens/text-entry.js","original":{"line":41,"column":14}},{"name":"document","generated":{"line":60,"column":20},"source":"screens/text-entry.js","original":{"line":41,"column":22}},{"name":"importNode","generated":{"line":60,"column":29},"source":"screens/text-entry.js","original":{"line":41,"column":31}},{"generated":{"line":60,"column":39},"source":"screens/text-entry.js","original":{"line":41,"column":22}},{"name":"template","generated":{"line":60,"column":40},"source":"screens/text-entry.js","original":{"line":41,"column":42}},{"name":"content","generated":{"line":60,"column":49},"source":"screens/text-entry.js","original":{"line":41,"column":51}},{"generated":{"line":60,"column":56},"source":"screens/text-entry.js","original":{"line":41,"column":22}},{"generated":{"line":60,"column":58},"source":"screens/text-entry.js","original":{"line":41,"column":60}},{"generated":{"line":60,"column":62},"source":"screens/text-entry.js","original":{"line":41,"column":22}},{"generated":{"line":60,"column":63},"source":"screens/text-entry.js","original":{"line":41,"column":8}},{"name":"clone","generated":{"line":62,"column":0},"source":"screens/text-entry.js","original":{"line":43,"column":8}},{"name":"querySelector","generated":{"line":62,"column":14},"source":"screens/text-entry.js","original":{"line":43,"column":14}},{"generated":{"line":62,"column":27},"source":"screens/text-entry.js","original":{"line":43,"column":8}},{"generated":{"line":62,"column":28},"source":"screens/text-entry.js","original":{"line":43,"column":28}},{"generated":{"line":62,"column":36},"source":"screens/text-entry.js","original":{"line":43,"column":8}},{"name":"addEventListener","generated":{"line":62,"column":38},"source":"screens/text-entry.js","original":{"line":43,"column":38}},{"generated":{"line":62,"column":54},"source":"screens/text-entry.js","original":{"line":43,"column":8}},{"generated":{"line":62,"column":55},"source":"screens/text-entry.js","original":{"line":43,"column":55}},{"generated":{"line":62,"column":62},"source":"screens/text-entry.js","original":{"line":43,"column":8}},{"generated":{"line":62,"column":64},"source":"screens/text-entry.js","original":{"line":43,"column":64}},{"generated":{"line":62,"column":81},"source":"screens/text-entry.js","original":{"line":43,"column":73}},{"name":"sendQandA","generated":{"line":63,"column":0},"source":"screens/text-entry.js","original":{"line":44,"column":12}},{"generated":{"line":64,"column":0},"source":"screens/text-entry.js","original":{"line":45,"column":9}},{"generated":{"line":64,"column":9},"source":"screens/text-entry.js","original":{"line":43,"column":8}},{"name":"element","generated":{"line":66,"column":0},"source":"screens/text-entry.js","original":{"line":47,"column":8}},{"name":"parent","generated":{"line":66,"column":16},"source":"screens/text-entry.js","original":{"line":47,"column":16}},{"generated":{"line":66,"column":22},"source":"screens/text-entry.js","original":{"line":47,"column":8}},{"name":"innerHTML","generated":{"line":66,"column":23},"source":"screens/text-entry.js","original":{"line":47,"column":23}},{"generated":{"line":66,"column":32},"source":"screens/text-entry.js","original":{"line":47,"column":8}},{"generated":{"line":66,"column":35},"source":"screens/text-entry.js","original":{"line":47,"column":35}},{"generated":{"line":66,"column":37},"source":"screens/text-entry.js","original":{"line":47,"column":8}},{"name":"element","generated":{"line":67,"column":0},"source":"screens/text-entry.js","original":{"line":48,"column":8}},{"name":"parent","generated":{"line":67,"column":16},"source":"screens/text-entry.js","original":{"line":48,"column":16}},{"generated":{"line":67,"column":22},"source":"screens/text-entry.js","original":{"line":48,"column":8}},{"name":"appendChild","generated":{"line":67,"column":23},"source":"screens/text-entry.js","original":{"line":48,"column":23}},{"generated":{"line":67,"column":34},"source":"screens/text-entry.js","original":{"line":48,"column":8}},{"name":"clone","generated":{"line":67,"column":35},"source":"screens/text-entry.js","original":{"line":48,"column":35}},{"generated":{"line":67,"column":40},"source":"screens/text-entry.js","original":{"line":48,"column":8}},{"name":"document","generated":{"line":69,"column":0},"source":"screens/text-entry.js","original":{"line":50,"column":8}},{"name":"querySelector","generated":{"line":69,"column":17},"source":"screens/text-entry.js","original":{"line":50,"column":17}},{"generated":{"line":69,"column":30},"source":"screens/text-entry.js","original":{"line":50,"column":8}},{"generated":{"line":69,"column":31},"source":"screens/text-entry.js","original":{"line":50,"column":31}},{"generated":{"line":69,"column":46},"source":"screens/text-entry.js","original":{"line":50,"column":8}},{"name":"focus","generated":{"line":69,"column":48},"source":"screens/text-entry.js","original":{"line":50,"column":48}},{"generated":{"line":69,"column":53},"source":"screens/text-entry.js","original":{"line":50,"column":8}},{"generated":{"line":70,"column":0},"source":"screens/text-entry.js","original":{"line":51,"column":5}},{"generated":{"line":71,"column":0},"source":"screens/text-entry.js","original":{"line":52,"column":1}},{"generated":{"line":71,"column":1},"source":"screens/text-entry.js","original":{"line":7,"column":7}}],"sources":{"screens/text-entry.js":"import { DOM } from '../learn-dom.js';\nimport { store } from '../../store/store-repo.js';\nimport { utils } from '../../utils/utils.js';\nimport { actions } from '../learn-actions.js';\nimport { types } from '../learn-types.js';\n\nexport const renderTextEntry = () => {\n\n    const { strategy, item, type } = store.getState();\n\n    if(type === types.NEXT_ITEM) {\n\n        let sendQandA = null;\n\n        const handleEnterPress = event => {\n            if(event.key === 'Enter') {\n                sendQandA();                \n            }\n        };\n\n        const { strategy } = store.getState();\n\n        const element = strategy.elements.filter(el => el.name === 'text-entry')[0];\n\n        if(!element) return;\n\n        const template = document.querySelector(`.${element.template}`);\n\n        sendQandA = () => {\n            if(!document.querySelector('.js-txt-input')) return;\n            const { item } = store.getState();\n            const answer = document.querySelector('.js-txt-input').value;\n            const qandA = { question: item[element.question], answer: answer }\n            actions.boundMarkAnswer(qandA);\n        };\n\n        // window.addEventListener('keypress', handleEnterPress);\n        \n        template.content.querySelector('span').innerHTML = item.genus;   \n\n        const clone = document.importNode(template.content, true);\n        \n        clone.querySelector('button').addEventListener('click', event => {\n            sendQandA();\n        });\n\n        element.parent.innerHTML = '';\n        element.parent.appendChild(clone);\n\n        document.querySelector('.js-txt-input').focus();\n    }\n};\n"},"lineCount":null}},"hash":"60c16c9a47158bdd90d1d54916b11962","cacheData":{"env":{}}}